scripts/generate_handlers.py
microsoft/teams/apps/__init__.py
microsoft/teams/apps/app.py
microsoft/teams/apps/app_events.py
microsoft/teams/apps/app_oauth.py
microsoft/teams/apps/app_plugins.py
microsoft/teams/apps/app_process.py
microsoft/teams/apps/container.py
microsoft/teams/apps/http_plugin.py
microsoft/teams/apps/http_stream.py
microsoft/teams/apps/options.py
microsoft/teams/apps/token_manager.py
microsoft/teams/apps/auth/__init__.py
microsoft/teams/apps/auth/jwt_middleware.py
microsoft/teams/apps/auth/remote_function_jwt_middleware.py
microsoft/teams/apps/auth/token_validator.py
microsoft/teams/apps/contexts/__init__.py
microsoft/teams/apps/contexts/client_context.py
microsoft/teams/apps/contexts/function_context.py
microsoft/teams/apps/events/__init__.py
microsoft/teams/apps/events/base.py
microsoft/teams/apps/events/registry.py
microsoft/teams/apps/events/types.py
microsoft/teams/apps/plugins/__init__.py
microsoft/teams/apps/plugins/metadata.py
microsoft/teams/apps/plugins/plugin_activity_event.py
microsoft/teams/apps/plugins/plugin_activity_response_event.py
microsoft/teams/apps/plugins/plugin_activity_sent_event.py
microsoft/teams/apps/plugins/plugin_base.py
microsoft/teams/apps/plugins/plugin_error_event.py
microsoft/teams/apps/plugins/plugin_start_event.py
microsoft/teams/apps/plugins/sender.py
microsoft/teams/apps/plugins/streamer.py
microsoft/teams/apps/routing/__init__.py
microsoft/teams/apps/routing/activity_context.py
microsoft/teams/apps/routing/activity_handlers.py
microsoft/teams/apps/routing/activity_route_configs.py
microsoft/teams/apps/routing/generated_handlers.py
microsoft/teams/apps/routing/router.py
microsoft/teams/apps/routing/type_helpers.py
microsoft/teams/apps/routing/type_validation.py
microsoft/teams/apps/utils/__init__.py
microsoft/teams/apps/utils/activity_utils.py
microsoft/teams/apps/utils/retry.py
microsoft/teams/apps/utils/timer.py
microsoft_teams_apps-2.0.0a5.dist-info/METADATA
microsoft_teams_apps-2.0.0a5.dist-info/WHEEL
microsoft_teams_apps-2.0.0a5.dist-info/entry_points.txt
microsoft_teams_apps-2.0.0a5.dist-info/RECORD
