Metadata-Version: 2.4
Name: microsoft-teams-apps
Version: 2.0.0a5
Summary: The app package for a Microsoft Teams agent
Author-email: Microsoft <TeamsAISDKFeedback@microsoft.com>
License-Expression: MIT
Keywords: agents,ai,bot,microsoft,teams
Requires-Python: <3.14,>=3.12
Requires-Dist: cryptography>=3.4.0
Requires-Dist: dependency-injector>=4.48.1
Requires-Dist: fastapi>=0.115.13
Requires-Dist: microsoft-teams-api
Requires-Dist: microsoft-teams-common
Requires-Dist: msal>=1.33.0
Requires-Dist: pyjwt[crypto]>=2.10.0
Requires-Dist: uvicorn>=0.34.3
Provides-Extra: graph
Requires-Dist: microsoft-teams-graph; extra == 'graph'
